Memory_Interface.v
module Memory_Interface 
(
  	input CLK,
  	input enable,
  	input memory_state,

  	input [3  : 0] frame_mask,
  	input [31 : 0] address,

  	inout [31 : 0] data,
    output reg  memory_done
);

 	reg [7 : 0] Memory [0 : 255];
    reg [31 : 0] data_in;

    localparam  READ        = 1'b0,
                WRITE       = 1'b1;

  	// Memory Interface Finite State Machine
  	reg [3 : 0] state;
	reg [3 : 0] next_state;

	localparam  STABLE      = 4'd0,
                B_0001      = 4'd1,
                B_0010      = 4'd2,
                B_0100      = 4'd3,
                B_1000      = 4'd4,
                H_0011_1    = 4'd5,
                H_0011_2    = 4'd6,
                H_1100_1    = 4'd7,
                H_1100_2    = 4'd8,
                W_1111_1    = 4'd9,
                W_1111_2    = 4'd10,
                W_1111_3    = 4'd11,
                W_1111_4    = 4'd12,
                FINISH      = 4'd13;

  	always @(posedge CLK)
    begin
        if (enable)
            state <= next_state;
        else    
            state <= STABLE; 
    end

    always @(*)
    begin
        case (state)
            STABLE : begin
                memory_done <= 1'b0;
                data_in <= 32'bz;
                
                if (frame_mask == 4'b0000)  next_state <= STABLE;

                if (frame_mask == 4'b0001)  next_state <= B_0001;
                if (frame_mask == 4'b0010)  next_state <= B_0010;
                if (frame_mask == 4'b0100)  next_state <= B_0100;
                if (frame_mask == 4'b1000)  next_state <= B_1000;

                if (frame_mask == 4'b0011)  next_state <= H_0011_1;
                if (frame_mask == 4'b1100)  next_state <= H_1100_1;

                if (frame_mask == 4'b1111)  next_state <= W_1111_1;
            end

            B_0001 : begin
                if (memory_state == READ)   data_in <= Memory[address + 3];
                if (memory_state == WRITE)  Memory[address + 3] <= data;
                next_state <= FINISH;
            end

            B_0010 : begin
                if (memory_state == READ)   data_in <= Memory[address + 2];
                if (memory_state == WRITE)  Memory[address + 2] <= data;
                next_state <= FINISH;
            end
            
            B_0100 : begin
                if (memory_state == READ)   data_in <= Memory[address + 1];
                if (memory_state == WRITE)  Memory[address + 1] <= data;
                next_state <= FINISH;
            end

            B_1000 : begin
                if (memory_state == READ)   data_in <= Memory[address + 0];
                if (memory_state == WRITE)  Memory[address + 0] <= data;
                next_state <= FINISH;
            end

            H_0011_1 : begin
                if (memory_state == READ)   data_in[15 : 8] <= Memory[address + 2];
                if (memory_state == WRITE)  Memory[address + 2] <= data[15 : 8];
                next_state <= H_0011_2;
            end

            H_0011_2 : begin
                if (memory_state == READ)   data_in[7 : 0] <= Memory[address + 3];
                if (memory_state == WRITE)  Memory[address + 3] <= data[7 : 0];
                next_state <= FINISH;
            end

            H_1100_1 : begin
                if (memory_state == READ)   data_in[15 : 8] <= Memory[address + 0];
                if (memory_state == WRITE)  Memory[address + 0] <= data[15 : 8];
                next_state <= H_1100_2;
            end

            H_1100_2 : begin
                if (memory_state == READ)   data_in[7 : 0] <= Memory[address + 1];
                if (memory_state == WRITE)  Memory[address + 1] <= data[7 : 0];
                next_state <= FINISH;
            end

            W_1111_1 : begin
                if (memory_state == READ)   data_in[31 : 24] <= Memory[address + 0];
                if (memory_state == WRITE)  Memory[address + 0] <= data[31 : 24]; 
                next_state <= W_1111_2;
            end

            W_1111_2 : begin
                if (memory_state == READ)   data_in[23 : 16] <= Memory[address + 1];
                if (memory_state == WRITE)  Memory[address + 1] <= data[23 : 16]; 
                next_state <= W_1111_3;
            end

            W_1111_3 : begin
                if (memory_state == READ)   data_in[15 : 8] <= Memory[address + 2];
                if (memory_state == WRITE)  Memory[address + 2] <= data[15 : 8]; 
                next_state <= W_1111_4;
            end

            W_1111_4 : begin
                if (memory_state == READ)   data_in[7 : 0] <= Memory[address + 3];
                if (memory_state == WRITE)  Memory[address + 3] <= data[7 : 0]; 
                next_state <= FINISH;
            end

            FINISH : begin
                memory_done <= 1'b1;
                next_state <= STABLE;
            end
        endcase
    end

    assign data = data_in;

endmodule

Load_Store_Unit.v
// `include "Memory_Interface.v"
`include "..\\Memory_Interface.v"

module Load_Store_Unit
(     
    input CLK,
    input enable,
    
    input  [6 : 0] opcode,          // Load/Store function
    input  [2 : 0] funct3,          // Load/Store function

    input       [31 : 0] address,        // Generated in Address Generator module
    input       [31 : 0] store_data,     // Connected to Register Source 2
    output reg  [31 : 0] load_data
);

    reg   memory_state;
    reg   [3 : 0] frame_mask;

    wire   memory_done;
    wire   [31 : 0] data;
    

    // Memory State and Frame Mask Generation
    always @(*) 
    begin
        {memory_state, frame_mask} = {1'bx, 4'bx};

        case ({funct3, opcode})
            // Load Instructions
            
            // LB and LBU
            10'b000_0000011, 10'b100_0000011: {memory_state, frame_mask} = 
            {   data_memory.READ, 
            {                   
                ~address[1] & ~address[0], 
                ~address[1] &  address[0], 
                 address[1] & ~address[0], 
                 address[1] &  address[0]
            }
            };

            // LH and LHU
            10'b001_0000011, 10'b101_0000011 : {memory_state, frame_mask} = 
            {   data_memory.READ,
            {                   
                {2{~address[1]}}, {2{address[1]}}
            }
            };

            // LW
            10'b010_0000011 : {memory_state, frame_mask} = {data_memory.READ, 4'b1111}; 
            
            // Store Instructions

            // SB
            10'b000_0100011 : {memory_state, frame_mask} = 
            {   data_memory.WRITE, 
            {                   
                ~address[1] & ~address[0], 
                ~address[1] &  address[0], 
                 address[1] & ~address[0], 
                 address[1] &  address[0]
            }
            }; 

            // SH
            10'b001_0100011 : {memory_state, frame_mask} = 
            {   data_memory.WRITE,
            {                   
                {2{~address[1]}}, {2{address[1]}}
            }
            }; 

            // SW
            10'b010_0100011 : {memory_state, frame_mask} = {data_memory.WRITE, 4'b1111};

            default : {memory_state, frame_mask} = {1'b0, 4'b0};
        endcase    
    end

    // Data Management in case of Store Instruction
    assign data = opcode == 7'b0100011 ? store_data : 32'bz;

    // Instantiating Memory Interface for Data Memory
    Memory_Interface data_memory 
    (
        .CLK(CLK),
        .enable(enable), 
        .memory_state(memory_state),
        .frame_mask(frame_mask),
        .address(address & 32'hFFFFFFFC), 
        .data(data), 
        .memory_done(memory_done)
    );
    
    // Latch condition when Loading
    always @(posedge memory_done)
    begin
        casex ({funct3, opcode})
            10'b000_0000011 : load_data <= { {24{data[7]}}, data[7 : 0]};       // LB
            10'b001_0000011 : load_data <= { {16{data[15]}}, data[15 : 0]};     // LH
            10'b100_0000011 : load_data <= { 24'b0, data[7 : 0]};               // LBU
            10'b101_0000011 : load_data <= { 16'b0, data[15 : 0]};              // LHU
            10'b010_0000011 : load_data <= data;                                // LW
        endcase    
    end

endmodule

Testbenches/TB_LSU.v
`include "..\\Load_Store_Unit.v"

module TB_LSU;

    reg CLK     = 1'b1;
    reg CLK_MEM = 1'b1;

    reg enable = 1'b0;

    reg  [6 : 0] opcode = 7'bz;
    reg  [2 : 0] funct3 = 3'bz;

    reg  [31 : 0] address = 32'bz;
    reg  [31 : 0] store_data = 32'bz; 
        
    wire [31 : 0] load_data; // variable is declared as "output reg" in the main module

    // Clock generation
    always #1 CLK_MEM = ~CLK_MEM;
    always #6 CLK = ~CLK;
    
    Load_Store_Unit uut 
    (
        CLK_MEM,
        enable,
        opcode,
        funct3,
        address,
        store_data,
        load_data
    );

    initial 
    begin

        $dumpfile("Test_LSU.vcd");
        $dumpvars(0, TB_LSU);

        $readmemh("..\\Instruction_Memory.txt", uut.data_memory.Memory);

        // Wait for a few clock cycles
        #12
        address = 32'd16;
        
        opcode  = 7'b0000011;
        funct3  = 3'b010;
        enable = 1'b1;

        #12
        enable = 1'b0;
        address = 32'bz;
        opcode = 7'bz;
        funct3 = 3'bz;

        #12
        address = 32'd19;

        opcode  = 7'b0000011;
        funct3  = 3'b100;
        enable = 1'b1;

        #12
        enable = 1'b0;
        address = 32'bz;
        opcode = 7'bz;
        funct3 = 3'bz;

        #12 
        address = 32'd16;
        
        opcode  = 7'b0000011;
        funct3  = 3'b010;
        enable = 1'b1;

        #12
        enable = 1'b0;
        address = 32'bz;
        opcode = 7'bz;
        funct3 = 3'bz;

        #100;
        $finish;
    end

endmodule

Testbenches/Test_LSU.vcd
$date
	Tue Aug 15 15:45:29 2023
$end
$version
	Icarus Verilog
$end
$timescale
	1s
$end
$scope module TB_LSU $end
$var wire 32 ! load_data [31:0] $end
$var reg 1 " CLK $end
$var reg 1 # CLK_MEM $end
$var reg 32 $ address [31:0] $end
$var reg 1 % enable $end
$var reg 3 & funct3 [2:0] $end
$var reg 7 ' opcode [6:0] $end
$var reg 32 ( store_data [31:0] $end
$scope module uut $end
$var wire 1 # CLK $end
$var wire 32 ) address [31:0] $end
$var wire 32 * data [31:0] $end
$var wire 1 % enable $end
$var wire 3 + funct3 [2:0] $end
$var wire 7 , opcode [6:0] $end
$var wire 32 - store_data [31:0] $end
$var wire 1 . memory_done $end
$var reg 4 / frame_mask [3:0] $end
$var reg 32 0 load_data [31:0] $end
$var reg 1 1 memory_state $end
$scope module data_memory $end
$var wire 1 # CLK $end
$var wire 32 2 address [31:0] $end
$var wire 32 3 data [31:0] $end
$var wire 1 % enable $end
$var wire 4 4 frame_mask [3:0] $end
$var wire 1 1 memory_state $end
$var parameter 4 5 B_0001 $end
$var parameter 4 6 B_0010 $end
$var parameter 4 7 B_0100 $end
$var parameter 4 8 B_1000 $end
$var parameter 4 9 FINISH $end
$var parameter 4 : H_0011_1 $end
$var parameter 4 ; H_0011_2 $end
$var parameter 4 < H_1100_1 $end
$var parameter 4 = H_1100_2 $end
$var parameter 1 > READ $end
$var parameter 4 ? STABLE $end
$var parameter 1 @ WRITE $end
$var parameter 4 A W_1111_1 $end
$var parameter 4 B W_1111_2 $end
$var parameter 4 C W_1111_3 $end
$var parameter 4 D W_1111_4 $end
$var reg 32 E data_in [31:0] $end
$var reg 1 . memory_done $end
$var reg 4 F next_state [3:0] $end
$var reg 4 G state [3:0] $end
$upscope $end
$upscope $end
$upscope $end
$enddefinitions $end
$comment Show the parameter values. $end
$dumpall
b1100 D
b1011 C
b1010 B
b1001 A
1@
b0 ?
0>
b1000 =
b111 <
b110 ;
b101 :
b1101 9
b100 8
b11 7
b10 6
b1 5
$end
#0
$dumpvars
b0 G
b0 F
bz E
b0 4
bz 3
bx00 2
01
bx 0
b0 /
0.
bz -
bz ,
bz +
bz *
bz )
bz (
bz '
bz &
0%
bz $
1#
1"
bx !
$end
#1
0#
#2
1#
#3
0#
#4
1#
#5
0#
#6
1#
0"
#7
0#
#8
1#
#9
0#
#10
1#
#11
0#
#12
b1001 F
b10000 2
01
b1111 /
b1111 4
1#
1"
1%
b10 &
b10 +
b11 '
b11 ,
b10000 $
b10000 )
#13
0#
#14
b1010 F
b0zzzzzzzzzzzzzzzzzzzzzzzz *
b0zzzzzzzzzzzzzzzzzzzzzzzz 3
b0zzzzzzzzzzzzzzzzzzzzzzzz E
b1001 G
1#
#15
0#
#16
b1011 F
b101zzzzzzzzzzzzzzzz *
b101zzzzzzzzzzzzzzzz 3
b101zzzzzzzzzzzzzzzz E
b1010 G
1#
#17
0#
#18
b1100 F
b10101000000zzzzzzzz *
b10101000000zzzzzzzz 3
b10101000000zzzzzzzz E
b1011 G
1#
0"
#19
0#
#20
b1101 F
b1010100000010000011 *
b1010100000010000011 3
b1010100000010000011 E
b1100 G
1#
#21
0#
#22
b1010100000010000011 !
b1010100000010000011 0
b0 F
1.
b1101 G
1#
#23
0#
#24
bz *
bz 3
bz E
0.
b0 G
bx00 2
01
b0 /
b0 4
1#
1"
bz &
bz +
bz '
bz ,
bz $
bz )
0%
#25
0#
#26
1#
#27
0#
#28
1#
#29
0#
#30
1#
0"
#31
0#
#32
1#
#33
0#
#34
1#
#35
0#
#36
b1 F
b10000 2
01
b1 /
b1 4
1#
1"
1%
b100 &
b100 +
b11 '
b11 ,
b10011 $
b10011 )
#37
0#
#38
b1101 F
b10000011 *
b10000011 3
b10000011 E
b1 G
1#
#39
0#
#40
b10000011 !
b10000011 0
b0 F
1.
b1101 G
1#
#41
0#
#42
b1 F
bz *
bz 3
bz E
0.
b0 G
1#
0"
#43
0#
#44
b1101 F
b10000011 *
b10000011 3
b10000011 E
b1 G
1#
#45
0#
#46
b0 F
1.
b1101 G
1#
#47
0#
#48
bz *
bz 3
bz E
0.
b0 G
bx00 2
01
b0 /
b0 4
1#
1"
bz &
bz +
bz '
bz ,
bz $
bz )
0%
#49
0#
#50
1#
#51
0#
#52
1#
#53
0#
#54
1#
0"
#55
0#
#56
1#
#57
0#
#58
1#
#59
0#
#60
b1001 F
b10000 2
01
b1111 /
b1111 4
1#
1"
1%
b10 &
b10 +
b11 '
b11 ,
b10000 $
b10000 )
#61
0#
#62
b1010 F
b0zzzzzzzzzzzzzzzzzzzzzzzz *
b0zzzzzzzzzzzzzzzzzzzzzzzz 3
b0zzzzzzzzzzzzzzzzzzzzzzzz E
b1001 G
1#
#63
0#
#64
b1011 F
b101zzzzzzzzzzzzzzzz *
b101zzzzzzzzzzzzzzzz 3
b101zzzzzzzzzzzzzzzz E
b1010 G
1#
#65
0#
#66
b1100 F
b10101000000zzzzzzzz *
b10101000000zzzzzzzz 3
b10101000000zzzzzzzz E
b1011 G
1#
0"
#67
0#
#68
b1101 F
b1010100000010000011 *
b1010100000010000011 3
b1010100000010000011 E
b1100 G
1#
#69
0#
#70
b1010100000010000011 !
b1010100000010000011 0
b0 F
1.
b1101 G
1#
#71
0#
#72
bz *
bz 3
bz E
0.
b0 G
bx00 2
01
b0 /
b0 4
1#
1"
bz &
bz +
bz '
bz ,
bz $
bz )
0%
