Memory_Interface.v
module Memory_Interface 
(
  	input CLK,
  	input enable,
  	input memory_state,

  	input [3  : 0] frame_mask,
  	input [31 : 0] address,

  	inout [31 : 0] data,
    output reg memory_done
);

 	reg [7 : 0] Memory [0 : 1023];
    reg [31 : 0] data_in;

    localparam  READ        = 1'b0,
                WRITE       = 1'b1;

  	// Memory Interface Finite State Machine
  	reg [3 : 0] state;
	reg [3 : 0] next_state;

	localparam  STABLE      = 4'd0,
                B_0001      = 4'd1,
                B_0010      = 4'd2,
                B_0100      = 4'd3,
                B_1000      = 4'd4,
                H_0011_1    = 4'd5,
                H_0011_2    = 4'd6,
                H_1100_1    = 4'd7,
                H_1100_2    = 4'd8,
                W_1111_1    = 4'd9,
                W_1111_2    = 4'd10,
                W_1111_3    = 4'd11,
                W_1111_4    = 4'd12,
                FINISH      = 4'd13;

  	always @(posedge CLK)
    begin
        if (enable)
            state <= next_state;
        else    
            state <= STABLE; 
    end
    
    always @(*)
    begin
        next_state = 'bx;

        
        
        case (state)
            STABLE : begin

                memory_done <= 1'b0;
                data_in <= 32'bz;
                
                if (frame_mask == 4'b0000)  next_state = STABLE;

                if (frame_mask == 4'b0001)  next_state = B_0001;
                if (frame_mask == 4'b0010)  next_state = B_0010;
                if (frame_mask == 4'b0100)  next_state = B_0100;
                if (frame_mask == 4'b1000)  next_state = B_1000;

                if (frame_mask == 4'b0011)  next_state = H_0011_1;
                if (frame_mask == 4'b1100)  next_state = H_1100_1;

                if (frame_mask == 4'b1111)  next_state = W_1111_1;
            end

            B_0001 : begin
                if (memory_state == READ)   data_in = Memory[address + 3];
                if (memory_state == WRITE)  Memory[address + 3] <= data;
                next_state = FINISH;
            end

            B_0010 : begin
                if (memory_state == READ)   data_in = Memory[address + 2];
                if (memory_state == WRITE)  Memory[address + 2] <= data;
                next_state = FINISH;
            end
            
            B_0100 : begin
                if (memory_state == READ)   data_in = Memory[address + 1];
                if (memory_state == WRITE)  Memory[address + 1] <= data;
                next_state = FINISH;
            end

            B_1000 : begin
                if (memory_state == READ)   data_in = Memory[address + 0];
                if (memory_state == WRITE)  Memory[address + 0] <= data;
                next_state = FINISH;
            end

            H_0011_1 : begin
                if (memory_state == READ)   data_in[15 : 8] <= Memory[address + 2];
                if (memory_state == WRITE)  Memory[address + 2] <= data[15 : 8];
                next_state = H_0011_2;
            end

            H_0011_2 : begin
                if (memory_state == READ)   data_in[7 : 0] <= Memory[address + 3];
                if (memory_state == WRITE)  Memory[address + 3] <= data[7 : 0];
                next_state = FINISH;
            end

            H_1100_1 : begin
                if (memory_state == READ)   data_in[15 : 8] <= Memory[address + 0];
                if (memory_state == WRITE)  Memory[address + 0] <= data[15 : 8];
                next_state = H_1100_2;
            end

            H_1100_2 : begin
                if (memory_state == READ)   data_in[7 : 0] <= Memory[address + 1];
                if (memory_state == WRITE)  Memory[address + 1] <= data[7 : 0];
                next_state = FINISH;
            end

            W_1111_1 : begin
                if (memory_state == READ)   data_in[31 : 24] <= Memory[address + 0];
                if (memory_state == WRITE)  Memory[address + 0] <= data[31 : 24]; 
                next_state = W_1111_2;
            end

            W_1111_2 : begin
                if (memory_state == READ)   data_in[23 : 16] <= Memory[address + 1];
                if (memory_state == WRITE)  Memory[address + 1] <= data[23 : 16]; 
                next_state = W_1111_3;
            end

            W_1111_3 : begin
                if (memory_state == READ)   data_in[15 : 8] <= Memory[address + 2];
                if (memory_state == WRITE)  Memory[address + 2] <= data[15 : 8]; 
                next_state = W_1111_4;
            end

            W_1111_4 : begin
                if (memory_state == READ)   data_in[7 : 0] <= Memory[address + 3];
                if (memory_state == WRITE)  Memory[address + 3] <= data[7 : 0]; 
                next_state = FINISH;
            end

            FINISH : begin
                memory_done = 1'b1;
                next_state = STABLE;
            end
        endcase
    end

    assign data = data_in;

    /*
	always @(*) begin

	  if (enable) begin
	    if (address <= 255) begin // Check if address is within memory range

	      if (memory_state) begin         // Write operation

	        case (frame_mask)
	          // Store Byte 
	          4'b0001 : memory[address + 3] = data;
	          4'b0010 : memory[address + 2] = data;
	          4'b0100 : memory[address + 1] = data;
	          4'b1000 : memory[address + 0] = data;
	          // Store Half-word 
	          4'b0011 : begin
	            memory[address + 2] = data;
	          end
	          4'b1100 : memory[address + 0] = data;
	        endcase

			
	      end 
	      else if (!memory_state) begin   // Read operation



	      end
	    end
	  end
	end
    */

endmodule

Testbenches/TB_Mem.v
`include "..\\Memory_Interface.v"

module TB_Mem;

    reg CLK = 1'b0;
    reg reset;

    reg enable;
    reg memory_state;

    reg [3 : 0] frame_mask;

    reg [31 : 0] address;
    
    wire [31 : 0] data;
    reg  [31 : 0] data_reg;

    assign data = data_reg;

    wire memory_done;

    Memory_Interface uut 
    (
        CLK,
        enable,
        memory_state,
        frame_mask,
        address,
        data,
        memory_done
    );

    // Clock generation
    always #1 CLK = ~CLK;
    
    // Memory Initialize
    

    initial begin

        $dumpfile("Test_Mem.vcd");
        $dumpvars(0, TB_Mem);

        $readmemh("..\\Instruction_Memory.txt", uut.Memory);

        data_reg = 32'bz;

        // Reset
        reset = 1'b1;
        enable = 1'b0;
        address = 32'b0;

        // Wait for a few clock cycles
        #10;
        reset = 1'b0;

        // Fetch Test
        #1 enable = 1'b1;
        memory_state = uut.READ;
        frame_mask = 4'b1111;
        address = 32'h04;
        #10
        enable = 1'b0;
        $display ("--> Testing Fetch Operation: ADDRESS = %h\tDATA = %h\n", address, data);
        #10;

        // Write operation
        enable = 1'b1;
        memory_state = uut.WRITE;
        address = 32'h04;
        frame_mask = 4'b0011;
        data_reg = 16'hFD;
        #6
        enable = 1'b0;
        data_reg = 32'bz;
        $display ("--> Testing Write Operation: ADDRESS = %h\tDATA = %h\n", address, data);
        #10;

        // Read operation
        enable = 1'b1;
        memory_state = uut.READ;
        frame_mask = 4'b1111;
        address = 32'h04;
        #10
        enable = 1'b0;
        $display ("--> Testing Read Operation: ADDRESS = %h\tDATA = %h\n", address, data);
        #10
        $finish;
    end
endmodule

Testbenches/Test_Mem.vcd
$date
	Sun Aug 13 16:44:44 2023
$end
$version
	Icarus Verilog
$end
$timescale
	1s
$end
$scope module TB_Mem $end
$var wire 32 ! data [31:0] $end
$var wire 1 " memory_done $end
$var reg 1 # CLK $end
$var reg 32 $ address [31:0] $end
$var reg 32 % data_reg [31:0] $end
$var reg 1 & enable $end
$var reg 4 ' frame_mask [3:0] $end
$var reg 1 ( memory_state $end
$var reg 1 ) reset $end
$scope module uut $end
$var wire 1 # CLK $end
$var wire 32 * address [31:0] $end
$var wire 32 + data [31:0] $end
$var wire 1 & enable $end
$var wire 4 , frame_mask [3:0] $end
$var wire 1 ( memory_state $end
$var parameter 4 - B_0001 $end
$var parameter 4 . B_0010 $end
$var parameter 4 / B_0100 $end
$var parameter 4 0 B_1000 $end
$var parameter 4 1 FINISH $end
$var parameter 4 2 H_0011_1 $end
$var parameter 4 3 H_0011_2 $end
$var parameter 4 4 H_1100_1 $end
$var parameter 4 5 H_1100_2 $end
$var parameter 1 6 READ $end
$var parameter 4 7 STABLE $end
$var parameter 1 8 WRITE $end
$var parameter 4 9 W_1111_1 $end
$var parameter 4 : W_1111_2 $end
$var parameter 4 ; W_1111_3 $end
$var parameter 4 < W_1111_4 $end
$var reg 32 = data_in [31:0] $end
$var reg 1 " memory_done $end
$var reg 4 > next_state [3:0] $end
$var reg 4 ? state [3:0] $end
$upscope $end
$upscope $end
$enddefinitions $end
$comment Show the parameter values. $end
$dumpall
b1100 <
b1011 ;
b1010 :
b1001 9
18
b0 7
06
b1000 5
b111 4
b110 3
b101 2
b1101 1
b100 0
b11 /
b10 .
b1 -
$end
#0
$dumpvars
bx ?
bx >
bx =
bx ,
bx +
b0 *
1)
x(
bx '
0&
bz %
b0 $
0#
x"
bx !
$end
#1
bz !
bz +
bz =
0"
b0 ?
1#
#2
0#
#3
1#
#4
0#
#5
1#
#6
0#
#7
1#
#8
0#
#9
1#
#10
0#
0)
#11
b0zzzzzzzzzzzzzzzzzzzzzzzz !
b0zzzzzzzzzzzzzzzzzzzzzzzz +
b0zzzzzzzzzzzzzzzzzzzzzzzz =
b1001 ?
b1010 >
1#
b100 $
b100 *
b1111 '
b1111 ,
0(
1&
#12
0#
#13
b10000zzzzzzzzzzzzzzzz !
b10000zzzzzzzzzzzzzzzz +
b10000zzzzzzzzzzzzzzzz =
b1011 >
b1010 ?
1#
#14
0#
#15
b1000000000101zzzzzzzz !
b1000000000101zzzzzzzz +
b1000000000101zzzzzzzz =
b1100 >
b1011 ?
1#
#16
0#
#17
b100000000010110010011 !
b100000000010110010011 +
b100000000010110010011 =
b1101 >
b1100 ?
1#
#18
0#
#19
1"
b0 >
b1101 ?
1#
#20
0#
#21
bz !
bz +
bz =
0"
b1001 >
b0 ?
1#
0&
#22
0#
#23
1#
#24
0#
#25
1#
#26
0#
#27
1#
#28
0#
#29
1#
#30
0#
#31
b101 ?
b110 >
1#
b11111101 !
b11111101 +
b11111101 %
b11 '
b11 ,
1(
1&
#32
0#
#33
b1101 >
b110 ?
1#
#34
0#
#35
1"
b0 >
b1101 ?
1#
#36
0#
#37
0"
b0 ?
b101 >
1#
bz !
bz +
bz %
0&
#38
0#
#39
1#
#40
0#
#41
1#
#42
0#
#43
1#
#44
0#
#45
1#
#46
0#
#47
b0zzzzzzzzzzzzzzzzzzzzzzzz !
b0zzzzzzzzzzzzzzzzzzzzzzzz +
b0zzzzzzzzzzzzzzzzzzzzzzzz =
b1001 ?
b1010 >
1#
b1111 '
b1111 ,
0(
1&
#48
0#
#49
b10000zzzzzzzzzzzzzzzz !
b10000zzzzzzzzzzzzzzzz +
b10000zzzzzzzzzzzzzzzz =
b1011 >
b1010 ?
1#
#50
0#
#51
b1000000000000zzzzzzzz !
b1000000000000zzzzzzzz +
b1000000000000zzzzzzzz =
b1100 >
b1011 ?
1#
#52
0#
#53
b100000000000011111101 !
b100000000000011111101 +
b100000000000011111101 =
b1101 >
b1100 ?
1#
#54
0#
#55
1"
b0 >
b1101 ?
1#
#56
0#
#57
bz !
bz +
bz =
0"
b1001 >
b0 ?
1#
0&
