Modules_Feature/AXI4_Lite_Interface/AXI4_write.v
module AXI4_write #(parameter ADDRESS_WIDTH = 2)
(
	input axi_clk,
	input resetn,   //axi is reset low

	// write address channel
	input [ADDRESS_WIDTH -  1 : 0] write_addr,
	input write_addr_valid,
	output reg write_addr_ready,

	// write data channel
	input [31 : 0] write_data,
	input write_data_valid,
	output reg write_data_ready,

	// write response channel	
	output [ADDRESS_WIDTH - 1 : 0] write_resp,
	input write_resp_ready,
	output reg write_resp_valid,
	
	output [31 : 0] data_out,                   //data output to external logic
	output [ADDRESS_WIDTH - 1 : 0] addr_out,    // address output to external logic
	output data_valid		                    // signal indicating output data and address are valid
);

	reg addr_done;
	reg data_done;

	// flip flops for latching data
	reg [31 : 0] data_latch;
	reg [ADDRESS_WIDTH - 1 : 0]  addr_latch;

	assign data_out = data_latch;
	assign addr_out = addr_latch;

	assign data_valid = data_done & addr_done;

	assign write_resp = {ADDRESS_WIDTH{1'b0}}; // always indicate OKAY status for writes

	// write address handshake
	always @(posedge axi_clk)
	begin
		if(~resetn | (write_addr_valid & write_addr_ready) )
			write_addr_ready <= 0;
		else if(~write_addr_ready & write_addr_valid)
			write_addr_ready <= 1;
	end

	// write data handshake
	always @(posedge axi_clk)
	begin
		if(~resetn | (write_data_valid & write_data_ready) )
			write_data_ready <= 0;
		else if(~write_data_ready & write_data_valid)
			write_data_ready <= 1;
	end

	// keep track of which handshakes completed
	always @(posedge axi_clk)
	begin
		if(resetn == 0 || (addr_done & data_done) ) // reset or both phases done
		begin
			addr_done <= 0;
			data_done <= 0;
		end
		else
		begin	
			if(write_addr_valid & write_addr_ready) // look for addr handshake
				addr_done <= 1;
		
			if(write_data_valid & write_data_ready) // look for data handshake
				data_done <= 1;	
		end
	end

	// latching logic
	always @(posedge axi_clk)
	begin
		if(resetn == 0) // reset values
		begin
			data_latch <= 32'd0;
			addr_latch <= {ADDRESS_WIDTH{1'b0}};
		end
		else
		begin
			if(write_data_valid & write_data_ready) // look for data handshake
				data_latch <= write_data;
			
			if(write_addr_valid & write_addr_ready) // look for address handshake
				addr_latch <= write_addr;
		end
	end

	// write response logic
	always @(posedge axi_clk)
	begin	
		if(resetn == 0 | (write_resp_valid & write_resp_ready))
			write_resp_valid <= 0;
		else if(~write_resp_valid & (data_done & addr_done))
			write_resp_valid <= 1;	
	end

endmodule

Modules_Feature/AXI4_Lite_Interface/AXI4_write_Testbench.v
`include "AXI4_write.v"

module AXI4_write_Testbench;

parameter ADDRESS_WIDTH = 2;

reg axi_clk = 1'b1;
reg resetn = 1'b0;

always #5 axi_clk = ~axi_clk;

// write address channel
reg [ADDRESS_WIDTH - 1 : 0] write_addr;
reg write_addr_valid;
wire write_addr_ready;

// write data channel
reg [31 : 0] write_data;
reg write_data_valid;
wire write_data_ready;

// write response channel	
wire [ADDRESS_WIDTH - 1 : 0] write_resp;
reg write_resp_ready;
wire write_resp_valid;

// four test registers
reg  [31 : 0] memory [2**ADDRESS_WIDTH : 0];
wire [ADDRESS_WIDTH - 1  : 0] write_address;
wire [31 : 0] rdata_in;
wire write_enable;

AXI4_write #(.ADDRESS_WIDTH(ADDRESS_WIDTH)) uut 
(
    .axi_clk(axi_clk),
    .resetn(resetn),

    .write_addr(write_addr),
    .write_addr_valid(write_addr_valid),
    .write_addr_ready(write_addr_ready),

    .write_data(write_data),
    .write_data_valid(write_data_valid),
    .write_data_ready(write_data_ready),

    .write_resp(write_resp),
    .write_resp_ready(write_resp_ready),
    .write_resp_valid(write_resp_valid),

    .data_out(rdata_in),
    .addr_out(write_address),
    .data_valid(write_enable)
);

integer i;
// write logic for a test memory
always @(posedge axi_clk)
begin
	if(resetn == 0)
	begin
		for(i = 0 ; i < 4 ; i = i + 1)
			memory[i] <= 0;
	end
	else if(write_enable)
		memory[write_address] <= rdata_in;
end


initial begin
    $dumpfile("AXI4_write.vcd");
    $dumpvars(0, AXI4_write_Testbench);

    // Initialize signals
    write_addr = 2'b0;
    write_addr_valid = 0;
    write_data = 0;
    write_data_valid = 0;
    write_resp_ready = 0;
    // Deassert reset
    #10 resetn = 1'b1;
    // Wait for a few clock cycles
    #20;

    // Here, we will write data to memory[0] and memory[1]
    // Set write address and data
    write_addr = 2'b00;
    write_data = 32'hA5A5A5A5;
    // Assert write address and data valid
    write_addr_valid = 1'b1;
    write_data_valid = 1'b1;

    // Wait for write address and data to be accepted
    repeat (10) @(posedge axi_clk);
    write_addr_valid = 1'b0;
    write_data_valid = 1'b0;

    // Wait for write response to be valid
    repeat (10) @(posedge axi_clk);

    // Check write response
    if (write_resp_valid) begin
        case (write_resp)
            2'b00: $display("Write transaction to memory[0] successful");
            2'b01: $display("Write transaction to memory[1] successful");
            default: $display("Write transaction failed");
        endcase
    end
    else begin
        $display("Write response not received");
    end

    // Repeat for another write transaction
    // Set write address and data
    write_addr = 2'b01;
    write_data = 32'h5A5A5A5A;

    // Assert write address and data valid
    write_addr_valid = 1'b1;
    write_data_valid = 1'b1;

    // Wait for write address and data to be accepted
    repeat (10) @(posedge axi_clk);
    write_addr_valid = 1'b0;
    write_data_valid = 1'b0;

    // Wait for write response to be valid
    repeat (10) @(posedge axi_clk);

    // Check write response
    if (write_resp_valid) begin
        case (write_resp)
            2'b00: $display("Write transaction to memory[0] successful");
            2'b01: $display("Write transaction to memory[1] successful");
            default: $display("Write transaction failed");
        endcase
    end
    else begin
        $display("Write response not received");
    end

    #10;
    $finish;
end

endmodule

Modules_Feature/AXI4_Lite_Interface/AXI4_write.vcd
$date
	Tue Aug 29 21:31:20 2023
$end
$version
	Icarus Verilog
$end
$timescale
	1s
$end
$scope module AXI4_write_Testbench $end
$var wire 2 ! write_resp [1:0] $end
$var wire 1 " write_resp_valid $end
$var wire 1 # write_enable $end
$var wire 1 $ write_data_ready $end
$var wire 2 % write_address [1:0] $end
$var wire 1 & write_addr_ready $end
$var wire 32 ' rdata_in [31:0] $end
$var parameter 32 ( ADDRESS_WIDTH $end
$var reg 1 ) axi_clk $end
$var reg 1 * resetn $end
$var reg 2 + write_addr [1:0] $end
$var reg 1 , write_addr_valid $end
$var reg 32 - write_data [31:0] $end
$var reg 1 . write_data_valid $end
$var reg 1 / write_resp_ready $end
$var integer 32 0 i [31:0] $end
$scope module uut $end
$var wire 2 1 addr_out [1:0] $end
$var wire 1 ) axi_clk $end
$var wire 32 2 data_out [31:0] $end
$var wire 1 # data_valid $end
$var wire 1 * resetn $end
$var wire 2 3 write_addr [1:0] $end
$var wire 1 , write_addr_valid $end
$var wire 32 4 write_data [31:0] $end
$var wire 1 . write_data_valid $end
$var wire 2 5 write_resp [1:0] $end
$var wire 1 / write_resp_ready $end
$var parameter 32 6 ADDRESS_WIDTH $end
$var reg 1 7 addr_done $end
$var reg 2 8 addr_latch [1:0] $end
$var reg 1 9 data_done $end
$var reg 32 : data_latch [31:0] $end
$var reg 1 & write_addr_ready $end
$var reg 1 $ write_data_ready $end
$var reg 1 " write_resp_valid $end
$upscope $end
$upscope $end
$enddefinitions $end
$comment Show the parameter values. $end
$dumpall
b10 6
b10 (
$end
#0
$dumpvars
b0 :
09
b0 8
07
b0 5
b0 4
b0 3
b0 2
b0 1
bx 0
0/
0.
b0 -
0,
b0 +
0*
1)
b0 '
0&
b0 %
0$
0#
0"
b0 !
$end
#5
0)
#10
1)
1*
#15
0)
#20
1)
#25
0)
#30
1$
1&
1)
1.
1,
b10100101101001011010010110100101 -
b10100101101001011010010110100101 4
#35
0)
#40
1#
0&
0$
19
17
b10100101101001011010010110100101 '
b10100101101001011010010110100101 2
b10100101101001011010010110100101 :
1)
#45
0)
#50
0#
1"
09
07
1$
1&
1)
#55
0)
#60
1#
0&
0$
19
17
1)
#65
0)
#70
0#
09
07
1$
1&
1)
#75
0)
#80
1#
0&
0$
19
17
1)
#85
0)
#90
0#
09
07
1$
1&
1)
#95
0)
#100
1#
0&
0$
19
17
1)
#105
0)
#110
0#
09
07
1$
1&
1)
#115
0)
#120
1#
0&
0$
19
17
0.
0,
1)
#125
0)
#130
0#
09
07
1)
#135
0)
#140
1)
#145
0)
#150
1)
#155
0)
#160
1)
#165
0)
#170
1)
#175
0)
#180
1)
#185
0)
#190
1)
#195
0)
#200
1)
#205
0)
#210
1)
#215
0)
#220
1.
1,
b1011010010110100101101001011010 -
b1011010010110100101101001011010 4
b1 +
b1 3
1)
#225
0)
#230
1$
1&
1)
#235
0)
#240
1#
0&
0$
19
17
b1 %
b1 1
b1 8
b1011010010110100101101001011010 '
b1011010010110100101101001011010 2
b1011010010110100101101001011010 :
1)
#245
0)
#250
0#
09
07
1$
1&
1)
#255
0)
#260
1#
0&
0$
19
17
1)
#265
0)
#270
0#
09
07
1$
1&
1)
#275
0)
#280
1#
0&
0$
19
17
1)
#285
0)
#290
0#
09
07
1$
1&
1)
#295
0)
#300
1#
0&
0$
19
17
1)
#305
0)
#310
0#
09
07
1$
1&
1)
#315
0)
#320
1#
0&
0$
19
17
0.
0,
1)
#325
0)
#330
0#
09
07
1)
