Modules_Feature/AXI4_Lite_Interface/AXI4_read.v
module AXI4_read #(parameter ADDRESS_WIDTH = 2)
(
    input axi_clk,
    input resetn,    // AXI is reset low

    // read address channel
    input [ADDRESS_WIDTH - 1 : 0] read_addr,
    input read_addr_valid,
    output reg read_addr_ready,

    // read data channel
    output reg [31 : 0] read_data,
    output reg read_data_valid,
    input read_data_ready,

    // read response channel
    output [ADDRESS_WIDTH - 1 : 0] read_resp,
    input read_resp_ready,
    output reg read_resp_valid,

    input [31 : 0] data_in,                     // data input from external logic
    input [ADDRESS_WIDTH - 1 : 0] addr_in,      // address input from external logic
    input data_valid                            // signal indicating input data and address are valid
);

    reg addr_done;
    reg data_done;

    // flip flops for latching data
    reg [31 : 0] data_latch;
    reg [ADDRESS_WIDTH - 1 : 0] addr_latch;

    always @(*) begin
        assign read_data = data_latch;
    end
    assign read_resp = {2'b0}; // always indicate OKAY status for reads

    // read address handshake
    always @(posedge axi_clk)
    begin
        if (~resetn | (read_addr_valid & read_addr_ready))
            read_addr_ready <= 0;
        else if (~read_addr_ready & read_addr_valid)
            read_addr_ready <= 1;
    end

    // read data handshake
    always @(posedge axi_clk)
    begin
        if (~resetn | (read_data_valid & read_data_ready))
            read_data_valid <= 0;
        else if (~read_data_valid & read_data_ready)
            read_data_valid <= 1;
    end

    // keep track of which handshakes completed
    always @(posedge axi_clk)
    begin
        if (resetn == 0 || (addr_done & data_done)) // reset or both phases done
        begin
            addr_done <= 0;
            data_done <= 0;
        end
        else
        begin    
            if (read_addr_valid & read_addr_ready) // look for address handshake
                addr_done <= 1;
            
            if (read_data_valid & read_data_ready) // look for data handshake
                data_done <= 1;    
        end
    end

    // latching logic
    always @(posedge axi_clk)
    begin
        if (resetn == 0) // reset values
        begin
            data_latch <= 32'd0;
            addr_latch <= {ADDRESS_WIDTH{1'b0}};
        end
        else
        begin
            if (read_data_valid & read_data_ready) // look for data handshake
                data_latch <= data_in;
            
            if (read_addr_valid & read_addr_ready) // look for address handshake
                addr_latch <= read_addr;
        end
    end

    // read response logic
    always @(posedge axi_clk)
    begin    
        if (resetn == 0 | (read_resp_valid & read_resp_ready))
            read_resp_valid <= 0;
        else if (~read_resp_valid & (data_done & addr_done))
            read_resp_valid <= 1;    
    end

endmodule

Modules_Feature/AXI4_Lite_Interface/AXI4_read_Testbench.v
`include "AXI4_read.v"

module AXI4_read_Testbench;

parameter ADDRESS_WIDTH = 2;

reg axi_clk = 1'b1;
reg resetn = 1'b0;

always #5 axi_clk = ~axi_clk;

// read address channel
reg [ADDRESS_WIDTH - 1 : 0] read_addr;
reg read_addr_valid;
wire read_addr_ready;

// read data channel
wire [31 : 0] read_data;
wire read_data_valid;
reg  read_data_ready;

// read response channel	
wire [ADDRESS_WIDTH - 1 : 0] read_resp;
reg read_resp_ready;
wire read_resp_valid;

// four test registers
reg  [31 : 0] memory [2**ADDRESS_WIDTH : 0];

// always @(posedge axi_clk or negedge axi_clk) begin
//     memory[0] = 32'hF;
//     memory[1] = 32'hA;    
// end

reg [ADDRESS_WIDTH - 1  : 0] read_address;
reg [31 : 0] rdata_in;
reg read_enable;

AXI4_read #(.ADDRESS_WIDTH(ADDRESS_WIDTH)) uut
(
    .axi_clk(axi_clk),
    .resetn(resetn),

    .read_addr(read_addr),
    .read_addr_valid(read_addr_valid),
    .read_addr_ready(read_addr_ready),

    .read_data(read_data),
    .read_data_valid(read_data_valid),
    .read_data_ready(read_data_ready),

    .read_resp(read_resp),
    .read_resp_ready(read_resp_ready),
    .read_resp_valid(read_resp_valid),

    .data_in(rdata_in),
    .addr_in(read_address),
    .data_valid(read_enable)
);

// read logic for a test memory
always @(posedge axi_clk)
begin
	if(resetn == 0)
	begin
		for(integer i = 0 ; i < 4 ; i = i + 1)
			memory[i] <= 0;
	end
	else if(read_enable)
		rdata_in <= memory[read_address];
end
    
initial begin
    $dumpfile("AXI4_read.vcd");
    $dumpvars(0, AXI4_read_Testbench);

    // Initialize signals
    memory[0] = 32'hA5A5A5A5;
    memory[1] = 32'hF;
    read_addr = 2'b0;
    read_addr_valid = 0;
    read_resp_ready = 0;
    // Deassert reset
    #10 resetn = 1'b1;
    // Wait for a few clock cycles
    #20;

    // Here, we will read data from memory[0]
    // Set read address
    read_enable = 1'b1;
    read_addr = 2'b00;
    // Assert read address and data valid
    read_addr_valid = 1'b1;

    // Wait for read address and data to be accepted
    repeat (10) @(posedge axi_clk);
    read_addr_valid = 1'b0;

    // Wait for read response to be valid
    repeat (10) @(posedge axi_clk);

    // Check read response
    if (read_resp_valid) begin
        case (read_resp)
            2'b00: $display("Read transaction from memory[0] successful");
            2'b01: $display("Read transaction from memory[1] successful");
            default: $display("Read transaction failed");
        endcase
    end
    else begin
        $display("Read response not received");
    end

    // Repeat for another read transaction
    // Set read address and data
    read_addr = 2'b01;

    // Assert read address and data valid
    read_enable = 1'b1;
    read_addr_valid = 1'b1;

    // Wait for read address and data to be accepted
    repeat (10) @(posedge axi_clk);
    read_addr_valid = 1'b0;

    // Wait for read response to be valid
    repeat (10) @(posedge axi_clk);

    // Check read response
    if (read_resp_valid) begin
        case (read_resp)
            2'b00: $display("Read transaction from memory[0] successful");
            2'b01: $display("Read transaction from memory[1] successful");
            default: $display("Read transaction failed");
        endcase
    end
    else begin
        $display("Read response not received");
    end

    // End simulation
    #10;
    $finish;
end

endmodule

Modules_Feature/AXI4_Lite_Interface/AXI4_read.vcd
$date
	Wed Aug 30 13:43:39 2023
$end
$version
	Icarus Verilog
$end
$timescale
	1s
$end
$scope module AXI4_read_Testbench $end
$var wire 2 ! read_resp [1:0] $end
$var wire 1 " read_resp_valid $end
$var wire 1 # read_data_valid $end
$var wire 32 $ read_data [31:0] $end
$var wire 1 % read_addr_ready $end
$var parameter 32 & ADDRESS_WIDTH $end
$var reg 1 ' axi_clk $end
$var reg 32 ( rdata_in [31:0] $end
$var reg 2 ) read_addr [1:0] $end
$var reg 1 * read_addr_valid $end
$var reg 2 + read_address [1:0] $end
$var reg 1 , read_data_ready $end
$var reg 1 - read_enable $end
$var reg 1 . read_resp_ready $end
$var reg 1 / resetn $end
$scope module uut $end
$var wire 2 0 addr_in [1:0] $end
$var wire 1 ' axi_clk $end
$var wire 32 1 data_in [31:0] $end
$var wire 1 - data_valid $end
$var wire 2 2 read_addr [1:0] $end
$var wire 1 * read_addr_valid $end
$var wire 1 , read_data_ready $end
$var wire 2 3 read_resp [1:0] $end
$var wire 1 . read_resp_ready $end
$var wire 1 / resetn $end
$var parameter 32 4 ADDRESS_WIDTH $end
$var reg 1 5 addr_done $end
$var reg 2 6 addr_latch [1:0] $end
$var reg 1 7 data_done $end
$var reg 32 8 data_latch [31:0] $end
$var reg 1 % read_addr_ready $end
$var reg 32 9 read_data [31:0] $end
$var reg 1 # read_data_valid $end
$var reg 1 " read_resp_valid $end
$upscope $end
$scope begin $ivl_for_loop0 $end
$var integer 32 : i [31:0] $end
$upscope $end
$upscope $end
$enddefinitions $end
$comment Show the parameter values. $end
$dumpall
b10 4
b10 &
$end
#0
$dumpvars
bx :
b0 9
b0 8
07
b0 6
05
b0 3
b0 2
bx 1
bx 0
0/
0.
x-
x,
bx +
0*
b0 )
bx (
1'
0%
b0 $
0#
0"
b0 !
$end
#5
0'
#10
1'
1/
#15
0'
#20
1'
#25
0'
#30
1%
1'
1*
1-
#35
0'
#40
0%
15
1'
#45
0'
#50
1%
1'
#55
0'
#60
0%
1'
#65
0'
#70
1%
1'
#75
0'
#80
0%
1'
#85
0'
#90
1%
1'
#95
0'
#100
0%
1'
#105
0'
#110
1%
1'
#115
0'
#120
0%
0*
1'
#125
0'
#130
1'
#135
0'
#140
1'
#145
0'
#150
1'
#155
0'
#160
1'
#165
0'
#170
1'
#175
0'
#180
1'
#185
0'
#190
1'
#195
0'
#200
1'
#205
0'
#210
1'
#215
0'
#220
1*
b1 )
b1 2
1'
#225
0'
#230
1%
1'
#235
0'
#240
0%
b1 6
1'
#245
0'
#250
1%
1'
#255
0'
#260
0%
1'
#265
0'
#270
1%
1'
#275
0'
#280
0%
1'
#285
0'
#290
1%
1'
#295
0'
#300
0%
1'
#305
0'
#310
1%
1'
#315
0'
#320
0%
0*
1'
