Modules_Feature/AXI4_Lite_Interface/AXI4_read.v
module AXI4_read #(parameter ADDRESS_WIDTH = 2)
(
    input axi_clk,
    input resetn,    // AXI is reset low

    // read address channel
    input [ADDRESS_WIDTH - 1 : 0] read_addr,
    input read_addr_valid,
    output reg read_addr_ready,

    // read data channel
    output reg [31 : 0] read_data,
    input  read_data_valid,
    output reg read_data_ready,

    // read response channel
    output [ADDRESS_WIDTH - 1 : 0] read_resp,
    input read_resp_ready,
    output reg read_resp_valid,

    output  [31 : 0] data_out,                   // data outout from external logic
    output [ADDRESS_WIDTH - 1 : 0] addr_out,     // address input from external logic
    output data_valid                            // signal indicating input data and address are valid
);

    reg addr_done;
    reg data_done;

    assign data_valid = data_done & addr_done;

    // flip flops for latching data
    reg [31 : 0] data_latch;
    reg [ADDRESS_WIDTH - 1 : 0] addr_latch;

    assign data_out = data_latch;
	assign addr_out = addr_latch;

    
    assign read_resp = {2'b0}; // always indicate OKAY status for reads

    // read address handshake
    always @(posedge axi_clk)
    begin
        if (~resetn | (read_addr_valid & read_addr_ready))
            read_addr_ready <= 0;
        else if (~read_addr_ready & read_addr_valid)
            read_addr_ready <= 1;
    end

    // read data handshake
    always @(posedge axi_clk)
    begin
        if (~resetn | (read_data_valid & read_data_ready))
            read_data_ready <= 0;
        else if (read_data_valid & ~read_data_ready)
            read_data_ready <= 1;
    end

    // keep track of which handshakes completed
    always @(posedge axi_clk)
    begin
        if (resetn == 0 || (addr_done & data_done)) // reset or both phases done
        begin
            addr_done <= 0;
            data_done <= 0;
        end
        else
        begin    
            if (read_addr_valid & read_addr_ready) // look for address handshake
                addr_done <= 1;
            
            if (read_data_valid & read_data_ready) // look for data handshake
                data_done <= 1;    
        end
    end

    // latching logic
    always @(posedge axi_clk)
    begin
        if (resetn == 0) // reset values
        begin
            data_latch <= 32'd0;
            addr_latch <= {ADDRESS_WIDTH{1'b0}};
        end
        else
        begin
            if (read_data_valid & read_data_ready) // look for data handshake
                read_data <= data_latch;
            
            if (read_addr_valid & read_addr_ready) // look for address handshake
                addr_latch <= read_addr;
        end
    end

    // read response logic
    always @(posedge axi_clk)
    begin    
        if (resetn == 0 | (read_resp_valid & read_resp_ready))
            read_resp_valid <= 0;
        else if (~read_resp_valid & (data_done & addr_done))
            read_resp_valid <= 1;    
    end

endmodule

Modules_Feature/AXI4_Lite_Interface/AXI4_read_Testbench.v
`include "AXI4_read.v"

module AXI4_read_Testbench;

parameter ADDRESS_WIDTH = 2;

reg axi_clk = 1'b1;
reg resetn = 1'b0;

always #5 axi_clk = ~axi_clk;

// read address channel
reg  [ADDRESS_WIDTH - 1 : 0] read_addr;
reg  read_addr_valid;
wire read_addr_ready;

// read data channel
wire  [31 : 0] read_data;
reg  read_data_valid;
wire read_data_ready;

// read response channel	
wire [ADDRESS_WIDTH - 1 : 0] read_resp;
reg  read_resp_ready;
wire read_resp_valid;

// four test registers
reg  [31 : 0] memory [2**ADDRESS_WIDTH : 0];
wire [ADDRESS_WIDTH - 1  : 0] read_address;
wire [31 : 0] rdata_out;
wire read_enable;

AXI4_read #(.ADDRESS_WIDTH(ADDRESS_WIDTH)) uut 
(
    .axi_clk(axi_clk),
    .resetn(resetn),

    .read_addr(read_addr),
    .read_addr_valid(read_addr_valid),
    .read_addr_ready(read_addr_ready),

    .read_data(read_data),
    .read_data_valid(read_data_valid),
    .read_data_ready(read_data_ready),

    .read_resp(read_resp),
    .read_resp_ready(read_resp_ready),
    .read_resp_valid(read_resp_valid),

    .data_out(rdata_out),
    .addr_out(read_address),
    .data_valid(read_enable)
);

reg [31 : 0] intermediate_wire = 0;
integer i;
// read logic for a test memory
always @(posedge axi_clk)
begin
	if(resetn == 0)
	begin
		for(i = 0 ; i < 4 ; i = i + 1)
			memory[i] <= 0;
	end
	else if(read_enable)
		intermediate_wire <= memory[read_address];
end

//assign rdata_out = intermediate_wire;
assign read_data = intermediate_wire;

initial begin
    $dumpfile("AXI4_read.vcd");
    $dumpvars(0, AXI4_read_Testbench);

    // Initialize signals
    memory[0] = 32'h5A5A5A5A;
    memory[1] = 32'hA5A5A5A5;
    read_addr = 2'b0;
    read_addr_valid = 0;
    read_data_valid = 0;
    read_resp_ready = 0;
    // Deassert reset
    #10 resetn = 1'b1;
    // Wait for a few clock cycles
    #20;

    // Here, we will read data to memory[0] and memory[1]
    // Set read address and data
    read_addr = 2'b00;
    // Assert read address and data valid
    read_addr_valid = 1'b1;
    read_data_valid = 1'b1;

    // Wait for read address and data to be accepted
    repeat (10) @(posedge axi_clk);
    read_addr_valid = 1'b0;
    read_data_valid = 1'b0;

    // Wait for read response to be valid
    repeat (10) @(posedge axi_clk);

    // Check read response
    if (read_resp_valid) begin
        case (read_resp)
            2'b00: $display("Read transaction from memory[0] successful");
            2'b01: $display("Read transaction from memory[1] successful");
            default: $display("Read transaction failed");
        endcase
    end
    else begin
        $display("Read response not received");
    end

    // Repeat for another read transaction
    // Set read address and data
    read_addr = 2'b01;

    // Assert read address and data valid
    read_addr_valid = 1'b1;
    read_data_valid = 1'b1;

    // Wait for read address and data to be accepted
    repeat (10) @(posedge axi_clk);
    read_addr_valid = 1'b0;
    read_data_valid = 1'b0;

    // Wait for read response to be valid
    repeat (10) @(posedge axi_clk);

    // Check read response
    if (read_resp_valid) begin
        case (read_resp)
            2'b00: $display("Read transaction from memory[0] successful");
            2'b01: $display("Read transaction from memory[1] successful");
            default: $display("Read transaction failed");
        endcase
    end
    else begin
        $display("Read response not received");
    end

    #10;
    $finish;
end

endmodule

Modules_Feature/AXI4_Lite_Interface/AXI4_read.vcd
$date
	Thu Aug 31 11:08:14 2023
$end
$version
	Icarus Verilog
$end
$timescale
	1s
$end
$scope module AXI4_read_Testbench $end
$var wire 32 ! rdata_out [31:0] $end
$var wire 2 " read_resp [1:0] $end
$var wire 1 # read_resp_valid $end
$var wire 1 $ read_enable $end
$var wire 1 % read_data_ready $end
$var wire 32 & read_data [31:0] $end
$var wire 2 ' read_address [1:0] $end
$var wire 1 ( read_addr_ready $end
$var parameter 32 ) ADDRESS_WIDTH $end
$var reg 1 * axi_clk $end
$var reg 32 + intermediate_wire [31:0] $end
$var reg 2 , read_addr [1:0] $end
$var reg 1 - read_addr_valid $end
$var reg 1 . read_data_valid $end
$var reg 1 / read_resp_ready $end
$var reg 1 0 resetn $end
$var integer 32 1 i [31:0] $end
$scope module uut $end
$var wire 2 2 addr_out [1:0] $end
$var wire 1 * axi_clk $end
$var wire 32 3 data_out [31:0] $end
$var wire 1 $ data_valid $end
$var wire 2 4 read_addr [1:0] $end
$var wire 1 - read_addr_valid $end
$var wire 1 . read_data_valid $end
$var wire 2 5 read_resp [1:0] $end
$var wire 1 / read_resp_ready $end
$var wire 1 0 resetn $end
$var parameter 32 6 ADDRESS_WIDTH $end
$var reg 1 7 addr_done $end
$var reg 2 8 addr_latch [1:0] $end
$var reg 1 9 data_done $end
$var reg 32 : data_latch [31:0] $end
$var reg 1 ( read_addr_ready $end
$var reg 32 ; read_data [31:0] $end
$var reg 1 % read_data_ready $end
$var reg 1 # read_resp_valid $end
$upscope $end
$upscope $end
$enddefinitions $end
$comment Show the parameter values. $end
$dumpall
b10 6
b10 )
$end
#0
$dumpvars
bx ;
b0 :
09
b0 8
07
b0 5
b0 4
b0 3
b0 2
bx 1
00
0/
0.
0-
b0 ,
b0 +
1*
0(
b0 '
bx &
0%
0$
0#
b0 "
b0 !
$end
#5
0*
#10
1*
10
#15
0*
#20
1*
#25
0*
#30
1%
1(
1*
1.
1-
#35
0*
#40
1$
0(
0%
19
17
b0 &
b0 ;
1*
#45
0*
#50
0$
b0x0xx0x00x0xx0x00x0xx0x00x0xx0x0 !
b0x0xx0x00x0xx0x00x0xx0x00x0xx0x0 3
b1011010010110100101101001011010 +
1#
09
07
1%
1(
1*
#55
0*
#60
1$
0(
0%
19
17
1*
#65
0*
#70
0$
09
07
1%
1(
1*
#75
0*
#80
1$
0(
0%
19
17
1*
#85
0*
#90
0$
09
07
1%
1(
1*
#95
0*
#100
1$
0(
0%
19
17
1*
#105
0*
#110
0$
09
07
1%
1(
1*
#115
0*
#120
1$
0(
0%
19
17
0.
0-
1*
#125
0*
#130
0$
09
07
1*
#135
0*
#140
1*
#145
0*
#150
1*
#155
0*
#160
1*
#165
0*
#170
1*
#175
0*
#180
1*
#185
0*
#190
1*
#195
0*
#200
1*
#205
0*
#210
1*
#215
0*
#220
1.
1-
b1 ,
b1 4
1*
#225
0*
#230
1%
1(
1*
#235
0*
#240
1$
0(
0%
19
17
b1 '
b1 2
b1 8
1*
#245
0*
#250
0$
bx0x00x0xx0x00x0xx0x00x0xx0x00x0x !
bx0x00x0xx0x00x0xx0x00x0xx0x00x0x 3
b10100101101001011010010110100101 +
09
07
1%
1(
1*
#255
0*
#260
1$
0(
0%
19
17
1*
#265
0*
#270
0$
09
07
1%
1(
1*
#275
0*
#280
1$
0(
0%
19
17
1*
#285
0*
#290
0$
09
07
1%
1(
1*
#295
0*
#300
1$
0(
0%
19
17
1*
#305
0*
#310
0$
09
07
1%
1(
1*
#315
0*
#320
1$
0(
0%
19
17
0.
0-
1*
#325
0*
#330
0$
09
07
1*
